halloumi_ses_user/__init__.py
halloumi_ses_user/py.typed
halloumi_ses_user/_jsii/__init__.py
halloumi_ses_user/_jsii/halloumi-ses@0.0.1.jsii.tgz
halloumi_ses_user-0.0.1.dist-info/LICENSE
halloumi_ses_user-0.0.1.dist-info/METADATA
halloumi_ses_user-0.0.1.dist-info/WHEEL
halloumi_ses_user-0.0.1.dist-info/top_level.txt
halloumi_ses_user-0.0.1.dist-info/RECORD
